flask_autosize/__init__.py
flask_autosize-6.0.1.20250916.dist-info/licenses/LICENSE.txt
flask_autosize-6.0.1.20250916.dist-info/METADATA
flask_autosize-6.0.1.20250916.dist-info/WHEEL
flask_autosize-6.0.1.20250916.dist-info/top_level.txt
flask_autosize-6.0.1.20250916.dist-info/RECORD
