Metadata-Version: 2.4
Name: flask_autosize
Version: 6.0.1.20250916
Summary: a package to use autosize in flask
Author-email: lix <xuzenglin@gmail.com>
License: BSD 3-Clause License
Project-URL: Homepage, https://github.com/lixxu/flask_autosize
Project-URL: Bug Tracker, https://github.com/lixxu/flask_autosize/issues
Keywords: star-rating
Classifier: Development Status :: 5 - Production/Stable
Classifier: Intended Audience :: Developers
Classifier: Programming Language :: Python :: 3
Classifier: License :: OSI Approved :: BSD License
Classifier: Operating System :: OS Independent
Requires-Python: >=3.10
License-File: LICENSE.txt
Requires-Dist: flask
Requires-Dist: flask_topassets
Dynamic: license-file
